{
  "project_info": {
    "project_number": "392841827787",
    "project_id": "health-care-app-791f6",
    "storage_bucket": "health-care-app-791f6.firebasestorage.app"
  },
  "client": [
    {
      "client_info": {
        "mobilesdk_app_id": "1:392841827787:android:8e6c6c81f6c2540ca4924e",
        "android_client_info": {
          "package_name": "com.example.health_care"
        }
      },
      "oauth_client": [],
      "api_key": [
        {
          "current_key": "AIzaSyBm2kRSx_CsFA1BhvcU8Is6sU5YxUcLwbI"
        }
      ],
      "services": {
        "appinvite_service": {
          "other_platform_oauth_client": []
        }
      }
    }
  ],
  "configuration_version": "1"
}